task1/Challenge/sreg7.sv
module sreg7 (
    input logic clk,
    input logic rst,
    input logic en,
    input logic data_in,
    output logic [7:1] data_out
);

    logic [7:1] sreg;

    always_ff @ (posedge clk)
        if(rst)
            sreg <= 7'b1;
        else if (en) begin
            sreg[7] <= sreg[6];
            sreg[6] <= sreg[5];
            sreg[5] <= sreg[4];
            sreg[4] <= sreg[3];
            sreg[3] <= sreg[2];
            sreg[2] <= sreg[1];
            sreg[1] <= data_in;
        end
        
        else
            ;
    assign data_out = sreg;
endmodule

task1/Challenge/lfsr.sv
module lfsr (
    input logic clk,
    input logic rst,
    input logic en, 
    output logic [7:1] data_out
);

    logic data_in;
    logic [7:1] reg7;

sreg7 shiftreg7 (
    .clk (clk),
    .rst (rst),
    .en (en),
    .data_in (data_in),
    .data_out (reg7)
);

always_ff @(posedge clk, posedge rst) begin
    if(en)
        data_in <= {reg7[3] ^ reg7[7]};
    else 
        ;
end

assign data_out = reg7;
endmodule

task1/Challenge/lfsr.vcd
$version Generated by VerilatedVcd $end
$date Thu Nov  2 14:33:43 2023 $end
$timescale 1ps $end

 $scope module TOP $end
  $var wire  1 # clk $end
  $var wire  7 & data_out [7:1] $end
  $var wire  1 % en $end
  $var wire  1 $ rst $end
  $scope module lfsr $end
   $var wire  1 # clk $end
   $var wire  1 ' data_in $end
   $var wire  7 & data_out [7:1] $end
   $var wire  1 % en $end
   $var wire  7 ( reg7 [7:1] $end
   $var wire  1 $ rst $end
   $scope module shiftreg7 $end
    $var wire  1 # clk $end
    $var wire  1 ' data_in $end
    $var wire  7 ( data_out [7:1] $end
    $var wire  1 % en $end
    $var wire  1 $ rst $end
    $var wire  7 ( sreg [7:1] $end
   $upscope $end
  $upscope $end
 $upscope $end
$enddefinitions $end


#0
1#
1$
1%
b0000000 &
0'
b0000000 (
#1
0#
#2
1#
b0000001 &
b0000001 (
#3
0#
#4
1#
#5
0#
#6
1#
#7
0#
#8
1#
0$
#9
0#
#10
1#
b0000010 &
b0000010 (
#11
0#
#12
1#
b0000100 &
b0000100 (
#13
0#
#14
1#
b0001000 &
1'
b0001000 (
#15
0#
#16
1#
b0010001 &
0'
b0010001 (
#17
0#
#18
1#
b0100010 &
b0100010 (
#19
0#
#20
1#
b1000100 &
b1000100 (
#21
0#
#22
1#
b0001000 &
b0001000 (
#23
0#
#24
1#
0%
b0010000 &
b0010000 (
